nl2ltl/__init__.py
nl2ltl/core.py
nl2ltl/exceptions.py
nl2ltl/helpers.py
nl2ltl/declare/__init__.py
nl2ltl/declare/base.py
nl2ltl/declare/declare.py
nl2ltl/declare/misc.py
nl2ltl/engines/__init__.py
nl2ltl/engines/base.py
nl2ltl/engines/grounding.py
nl2ltl/engines/utils.py
nl2ltl/engines/gpt/__init__.py
nl2ltl/engines/gpt/core.py
nl2ltl/engines/gpt/output.py
nl2ltl/engines/rasa/__init__.py
nl2ltl/engines/rasa/core.py
nl2ltl/engines/rasa/helpers.py
nl2ltl/engines/rasa/output.py
nl2ltl/filters/__init__.py
nl2ltl/filters/base.py
nl2ltl/filters/simple_filters.py
nl2ltl/filters/utils/__init__.py
nl2ltl/filters/utils/conflicts.py
nl2ltl/filters/utils/subsumptions.py
nl2ltl-0.0.6.dist-info/AUTHORS.md
nl2ltl-0.0.6.dist-info/LICENSE
nl2ltl-0.0.6.dist-info/METADATA
nl2ltl-0.0.6.dist-info/WHEEL
nl2ltl-0.0.6.dist-info/top_level.txt
nl2ltl-0.0.6.dist-info/RECORD
