Metadata-Version: 2.1
Name: nl2ltl
Version: 0.0.6
Summary: Natural Language (NL) to Linear Temporal Logic (LTL)
Author-email: Francesco Fuggitti <francesco.fuggitti@gmail.com>, Tathagata Chakraborti <tchakra2@ibm.com>
License: MIT License
Project-URL: Repository, https://github.com/IBM/nl2ltl
Project-URL: Issues, https://github.com/IBM/nl2ltl/issues
Keywords: natural language processing,linear temporal logics,generative ai,large language models,process automation,conversational agents
Classifier: Development Status :: 2 - Pre-Alpha
Classifier: Intended Audience :: Developers
Classifier: Intended Audience :: Science/Research
Classifier: Natural Language :: English
Classifier: License :: OSI Approved :: MIT License
Classifier: Operating System :: OS Independent
Classifier: Programming Language :: Python :: 3.10
Classifier: Topic :: Scientific/Engineering :: Artificial Intelligence
Classifier: Topic :: Scientific/Engineering :: Human Machine Interfaces
Classifier: Topic :: Scientific/Engineering :: Information Analysis
Requires-Python: <3.11,>=3.8
License-File: LICENSE
License-File: AUTHORS.md
Requires-Dist: pylogics
Requires-Dist: openai==1.12.0
Provides-Extra: rasa
Requires-Dist: rasa==3.6.16; extra == "rasa"
Provides-Extra: dev
Requires-Dist: codecov; extra == "dev"
Requires-Dist: mkdocs; extra == "dev"
Requires-Dist: markdown-include; extra == "dev"
Requires-Dist: pre-commit; extra == "dev"
Requires-Dist: pytest; extra == "dev"
Requires-Dist: pytest-cov; extra == "dev"
Requires-Dist: ruff; extra == "dev"
Requires-Dist: tox==3.27.1; extra == "dev"
